py360convert/__init__.py
py360convert/c2e.py
py360convert/e2c.py
py360convert/e2p.py
py360convert/utils.py
py360convert_modified-1.0.1.dist-info/LICENSE
py360convert_modified-1.0.1.dist-info/METADATA
py360convert_modified-1.0.1.dist-info/WHEEL
py360convert_modified-1.0.1.dist-info/entry_points.txt
py360convert_modified-1.0.1.dist-info/top_level.txt
py360convert_modified-1.0.1.dist-info/RECORD
