Metadata-Version: 2.1
Name: py360convert-modified
Version: 1.0.1
Summary: Convertion between cubemap and equirectangular and also to perspective planar.
Author-email: Andrea Lombardo <andrealombardo2m@gmail.com>
License: MIT License
Project-URL: Homepage, https://github.com/imandrealombardo/py360convert
Project-URL: Issues, https://github.com/imandrealombardo/py360convert/issues
Classifier: Development Status :: 3 - Alpha
Classifier: Intended Audience :: Developers
Classifier: Topic :: Artistic Software
Classifier: Topic :: Software Development :: Libraries
Classifier: License :: OSI Approved :: MIT License
Classifier: Programming Language :: Python :: 3
Classifier: Programming Language :: Python :: 3.7
Classifier: License :: OSI Approved :: MIT License
Classifier: Operating System :: OS Independent
Requires-Python: >=3.7
License-File: LICENSE
Requires-Dist: numpy
Requires-Dist: scipy
